httpsig/__init__.py
httpsig/requests_auth.py
httpsig/sign.py
httpsig/utils.py
httpsig/verify.py
httpsig/tests/__init__.py
httpsig/tests/rsa_private.pem
httpsig/tests/rsa_public.pem
httpsig/tests/test_signature.py
httpsig/tests/test_utils.py
httpsig/tests/test_verify.py
httpsig-1.3.0.dist-info/LICENSE.txt
httpsig-1.3.0.dist-info/METADATA
httpsig-1.3.0.dist-info/WHEEL
httpsig-1.3.0.dist-info/top_level.txt
httpsig-1.3.0.dist-info/zip-safe
httpsig-1.3.0.dist-info/RECORD
