Metadata-Version: 2.1
Name: httpsig
Version: 1.3.0
Summary: Secure HTTP request signing using the HTTP Signature draft specification
Home-page: https://github.com/ahknight/httpsig
Author: Adam Knight
Author-email: adam@movq.us
License: MIT
Keywords: http,authorization,api,web
Platform: UNKNOWN
Classifier: Development Status :: 5 - Production/Stable
Classifier: Environment :: Web Environment
Classifier: Intended Audience :: Developers
Classifier: License :: OSI Approved :: MIT License
Classifier: Operating System :: OS Independent
Classifier: Programming Language :: Python
Classifier: Programming Language :: Python :: 2.7
Classifier: Programming Language :: Python :: 3.4
Classifier: Programming Language :: Python :: 3.5
Classifier: Programming Language :: Python :: 3.6
Classifier: Programming Language :: Python :: 3.7
Classifier: Topic :: Internet :: WWW/HTTP
Classifier: Topic :: Software Development :: Libraries :: Python Modules
Requires-Dist: pycryptodome (<4,>=3)
Requires-Dist: six
